rovcontrol/__init__.py
rovcontrol/drivers/DriverTemp.py
rovcontrol/drivers/__init__.py
rovcontrol/drivers/abstract/ADCBlock.py
rovcontrol/drivers/abstract/PWMBlock.py
rovcontrol/drivers/abstract/__init__.py
rovcontrol/drivers/adc/ADCTemp.py
rovcontrol/drivers/adc/__init__.py
rovcontrol/drivers/com/ComTemp.py
rovcontrol/drivers/com/DummyCom.py
rovcontrol/drivers/com/WsCom.py
rovcontrol/drivers/com/__init__.py
rovcontrol/drivers/current/CurrentTemp.py
rovcontrol/drivers/current/__init__.py
rovcontrol/drivers/motor/MotorTemp.py
rovcontrol/drivers/motor/__init__.py
rovcontrol/drivers/pwm/PWMTemp.py
rovcontrol/drivers/pwm/__init__.py
rovcontrol-0.7.2.dist-info/METADATA
rovcontrol-0.7.2.dist-info/RECORD
rovcontrol-0.7.2.dist-info/WHEEL
rovcontrol-0.7.2.dist-info/top_level.txt
