Metadata-Version: 2.1
Name: rovcontrol
Version: 0.7.2
Summary: UNKNOWN
Home-page: https://gitlab.com/ld-cd/rovcontrol/
Author: Aled Cuda
Author-email: aledvirgil@gmail.com
License: MIT
Platform: UNKNOWN
Requires-Dist: websockets
